{"cameraMode":{"drawMode":0,"name":"Shaded","section":"Shading Mode"},"sceneLighting":true,"audioPlay":false,"sceneViewState":{"showFog":true,"showMaterialUpdate":false,"showSkybox":true,"showFlares":true,"showImageEffects":true,"showParticleSystems":true},"in2DMode":false,"pivot":{"x":29.04507827758789,"y":0.9949541687965393,"z":-1.6161001920700074},"rotation":{"x":0.2395685762166977,"y":-0.10252688825130463,"z":0.02604096755385399,"w":0.9653657674789429},"size":17.609832763671876,"orthographic":false}